prommis/__init__.py
prommis/conftest.py
prommis/test_package.py
prommis/_sphinx_extensions/chem.py
prommis/_testing_utils/__init__.py
prommis/_testing_utils/known_issues.py
prommis/cmi_precipitator/__init__.py
prommis/cmi_precipitator/aqueous_properties.py
prommis/cmi_precipitator/opt_based_precipitator.py
prommis/cmi_precipitator/precipitate_properties.py
prommis/cmi_precipitator/tests/__init__.py
prommis/cmi_precipitator/tests/test_aqueous_props.py
prommis/cmi_precipitator/tests/test_precipitate_props.py
prommis/cmi_precipitator/tests/test_precipitator.py
prommis/evaporation_pond/__init__.py
prommis/evaporation_pond/evaporation_pond.py
prommis/evaporation_pond/tests/__init__.py
prommis/evaporation_pond/tests/example_properties.py
prommis/evaporation_pond/tests/example_reactions.py
prommis/evaporation_pond/tests/test_evaporation_pond.py
prommis/examples/__init__.py
prommis/examples/uky_example.ipynb
prommis/examples/uky_flowsheet.png
prommis/examples/uky_fv.py
prommis/examples/util.py
prommis/examples/cmi_process_flowsheet/__init__.py
prommis/examples/cmi_process_flowsheet/cmi_process_adjustment_rxn_prop_pack.py
prommis/examples/cmi_process_flowsheet/cmi_process_dissolution_rxn_prop_pack.py
prommis/examples/cmi_process_flowsheet/cmi_process_flowsheet.py
prommis/examples/cmi_process_flowsheet/cmi_process_precipitation_rxn_prop_pack.py
prommis/examples/cmi_process_flowsheet/cmi_process_prop_pack.py
prommis/examples/cmi_process_flowsheet/tests/__init__.py
prommis/examples/cmi_process_flowsheet/tests/test_cmi_process_flowsheet.py
prommis/leaching/__init__.py
prommis/leaching/leach_flowsheet.py
prommis/leaching/leach_flowsheet_dynamic.py
prommis/leaching/leach_reactions.py
prommis/leaching/leach_solids_properties.py
prommis/leaching/leach_solution_properties.py
prommis/leaching/leach_train.py
prommis/leaching/leaching.json
prommis/leaching/leaching2.json
prommis/leaching/tests/__init__.py
prommis/leaching/tests/test_leach_flowsheet.py
prommis-0.8.0.dist-info/licenses/LICENSE.md
prommis-0.8.0.dist-info/METADATA
prommis-0.8.0.dist-info/WHEEL
prommis-0.8.0.dist-info/entry_points.txt
prommis-0.8.0.dist-info/top_level.txt
prommis-0.8.0.dist-info/RECORD
