Metadata-Version: 2.4
Name: prommis
Version: 0.8.0
Keywords: IDAES,energy systems,chemical engineering,process modeling
Classifier: Development Status :: 3 - Alpha
Classifier: Intended Audience :: End Users/Desktop
Classifier: Intended Audience :: Science/Research
Classifier: License :: OSI Approved :: BSD License
Classifier: Natural Language :: English
Classifier: Operating System :: MacOS
Classifier: Operating System :: Microsoft :: Windows
Classifier: Operating System :: Unix
Classifier: Programming Language :: Python
Classifier: Programming Language :: Python :: 3
Classifier: Programming Language :: Python :: 3.9
Classifier: Programming Language :: Python :: 3.10
Classifier: Programming Language :: Python :: 3.11
Classifier: Programming Language :: Python :: Implementation :: CPython
Classifier: Topic :: Scientific/Engineering :: Mathematics
Classifier: Topic :: Scientific/Engineering :: Chemistry
Classifier: Topic :: Software Development :: Libraries :: Python Modules
License-File: LICENSE.md
Requires-Dist: idaes-pse>=2.8.0
Requires-Dist: pyomo>=6.7.0
Provides-Extra: watertap
Requires-Dist: watertap>=1.4.0; extra == "watertap"
Provides-Extra: flowsheet-processor
Requires-Dist: idaes-flowsheet-processor>=0.1.dev4; extra == "flowsheet-processor"
Dynamic: license-file
